LICENSE
README.md
setup.py
aRST/__init__.py
aRST/script/__init__.py
aRST/script/align.py
aRST/script/callsys.py
aRST/script/check_input.py
aRST/script/do_scan.py
aRST/script/element.py
aRST/script/geom.py
aRST/script/head.py
aRST/script/initialization.py
aRST/script/main.py
aRST/script/spr.py
aRST/script/toolbox.py
aRST/script/alignment/__init__.py
aRST/script/alignment/do_alignment.py
aRST/script/exploration/__init__.py
aRST/script/exploration/assign_reaction.py
aRST/script/exploration/depotonation.py
aRST/script/exploration/interA.py
aRST/script/exploration/intraA.py
aRST/script/exploration/intraD.py
aRST/script/exploration/network.py
aRST/script/exploration/plot.py
aRST/script/exploration/prepare_afo.py
aRST/script/nanoreactor/__init__.py
aRST/script/nanoreactor/build_reaction.py
aRST/script/reactivity/__init__.py
aRST/script/reactivity/afo_features.py
aRST/script/reactivity/print_stuff.py
aRST_chem.egg-info/PKG-INFO
aRST_chem.egg-info/SOURCES.txt
aRST_chem.egg-info/dependency_links.txt
aRST_chem.egg-info/entry_points.txt
aRST_chem.egg-info/requires.txt
aRST_chem.egg-info/top_level.txt