Metadata-Version: 2.2
Name: aRST-chem
Version: 2.0.2
Summary: an Automated Reaction Search Tool
Home-page: https://git.rwth-aachen.de/bannwarthlab/aRST
Author: Ying Chen
Author-email: ying.chen@pc.rwth-aachen.de
License: MIT
Classifier: Development Status :: 1 - Planning
Classifier: Intended Audience :: Science/Research
Classifier: Operating System :: POSIX :: Linux
Classifier: Programming Language :: Python :: 3.9
License-File: LICENSE
Requires-Dist: billiard~=4.2.1
Requires-Dist: matplotlib~=3.7.5
Requires-Dist: molbar~=1.1.3
Requires-Dist: networkx~=3.1
Requires-Dist: numpy~=1.24.4
Requires-Dist: pandas~=2.0.3
Requires-Dist: read~=0.0.2
Requires-Dist: scipy~=1.10.1
Requires-Dist: setuptools~=70.0.0
Requires-Dist: toml~=0.10.2
Dynamic: author
Dynamic: author-email
Dynamic: classifier
Dynamic: description
Dynamic: description-content-type
Dynamic: home-page
Dynamic: license
Dynamic: requires-dist
Dynamic: summary
